orpl/__init__.py
orpl/__main__.py
orpl/baseline_removal.py
orpl/bubblegif.py
orpl/calibration.py
orpl/cosmic_ray.py
orpl/datatypes.py
orpl/file_io.py
orpl/metrics.py
orpl/normalization.py
orpl/pipelines.py
orpl/plot.py
orpl/synthetic.py
orpl/data/__init__.py
orpl/data/synthetic_presets.json
orpl/gui/__init__.py
orpl/gui/mplcanvas.py
orpl/gui/orplGUI.py
orpl/gui/uis/__init__.py
orpl/gui/uis/ui_mainWindow.py
orplib-1.0.10.dist-info/METADATA
orplib-1.0.10.dist-info/WHEEL
orplib-1.0.10.dist-info/top_level.txt
orplib-1.0.10.dist-info/RECORD
