Metadata-Version: 2.1
Name: orplib
Version: 1.0.10
Summary: Open Raman Processing Library
Home-page: https://github.com/mr-sheg/orpl
Author: Guillaume Sheehy
Author-email: guillaume.sheehy@polymtl.ca
License: MIT License
Classifier: Programming Language :: Python :: 3
Classifier: License :: OSI Approved :: MIT License
Classifier: Operating System :: OS Independent
Requires-Python: >=3.8
Requires-Dist: matplotlib >=3.5.1
Requires-Dist: numba >=0.55.1
Requires-Dist: numpy >=1.21.5
Requires-Dist: scipy >=1.7.3
Requires-Dist: pyperclip >=1.8.2
Requires-Dist: qtmodern >=0.2.0
Requires-Dist: PyQt5 >=5.15
Requires-Dist: ruamel.yaml >=0.17
Requires-Dist: sif-parser >=0.3.0
Requires-Dist: renishawWiRE >=0.1.16
